magicswitchbot/__init__.py
magicswitchbot/consts.py
magicswitchbot/device.py
magicswitchbot/discovery.py
magicswitchbot/models.py
pyMagicSwitchbot-1.1.4.dist-info/LICENSE.txt
pyMagicSwitchbot-1.1.4.dist-info/METADATA
pyMagicSwitchbot-1.1.4.dist-info/WHEEL
pyMagicSwitchbot-1.1.4.dist-info/top_level.txt
pyMagicSwitchbot-1.1.4.dist-info/RECORD
