Metadata-Version: 2.1
Name: pyMagicSwitchbot
Version: 1.1.4
Summary: Library to control Magic Switchbot devices
Home-page: https://github.com/ec-blaster/pyMagicSwitchbot
Author: Isidoro Aguilar Baeza
License: MIT
Classifier: Development Status :: 3 - Alpha
Classifier: Environment :: Other Environment
Classifier: Intended Audience :: Developers
Classifier: Operating System :: POSIX :: Linux
Classifier: Programming Language :: Python :: 3.10
Classifier: Topic :: Home Automation
Classifier: Topic :: Software Development :: Libraries :: Python Modules
License-File: LICENSE.txt
Requires-Dist: pycryptodome
Requires-Dist: bleak (>=0.17.0)
Requires-Dist: bleak-retry-connector (>=1.17.1)
